cloud_sdk/__init__.py
cloud_sdk/auth.py
cloud_sdk/calculator_client.py
cloud_sdk/checker.py
cloud_sdk/client_mock.py
cloud_sdk/config.py
cloud_sdk/keycloak_token.py
cloud_sdk/logger.py
cloud_sdk/order_service.py
cloud_sdk/portal.py
cloud_sdk/product_catalog.py
cloud_sdk/references.py
cloud_sdk/sdk.py
cloud_sdk/state_service_client.py
cloud_sdk/accountmanager_client/__init__.py
cloud_sdk/accountmanager_client/client.py
cloud_sdk/api_client/__init__.py
cloud_sdk/api_client/auth.py
cloud_sdk/api_client/auxiliary.py
cloud_sdk/api_client/base.py
cloud_sdk/api_client/error.py
cloud_sdk/api_client/http_client.py
cloud_sdk/api_client/pool.py
cloud_sdk/api_client/resource.py
cloud_sdk/api_client/service.py
cloud_sdk/api_client/utils.py
cloud_sdk/authorizer_client/__init__.py
cloud_sdk/authorizer_client/client.py
cloud_sdk/example/__init__.py
cloud_sdk/example/products.py
cloud_sdk/example/sstest.py
vtb_cloud_sdk-1.0.23.dist-info/METADATA
vtb_cloud_sdk-1.0.23.dist-info/WHEEL
vtb_cloud_sdk-1.0.23.dist-info/top_level.txt
vtb_cloud_sdk-1.0.23.dist-info/RECORD
