Metadata-Version: 2.1
Name: vtb-cloud-sdk
Version: 1.0.23
Summary: Client for VTB cloud
Home-page: https://bitbucket.region.vtb.ru/projects/PUOS/repos/cloud_sdk/
Author: Anton Tagunov
Author-email: atagunov@asdco.ru
License: Private
Platform: UNKNOWN
Requires-Dist: requests
Requires-Dist: python-dateutil
Requires-Dist: docopt
Requires-Dist: pytz
Requires-Dist: beautifulsoup4
Requires-Dist: lxml
Requires-Dist: python-keycloak
Requires-Dist: pyjwt
Requires-Dist: logbook
Requires-Dist: attrdict
Requires-Dist: vtb-py-logging
